xwolfapi/__init__.py
xwolfapi/constants.py
xwolfapi/exceptions.py
xwolfapi/client/__init__.py
xwolfapi/client/wolf.py
xwolfapi/helpers/__init__.py
xwolfapi/helpers/channel_helper.py
xwolfapi/helpers/command_handler.py
xwolfapi/helpers/messaging.py
xwolfapi/helpers/phrase_helper.py
xwolfapi/helpers/subscriber_helper.py
xwolfapi/helpers/utility.py
xwolfapi/helpers/websocket.py
xwolfapi/models/__init__.py
xwolfapi/models/channel.py
xwolfapi/models/command.py
xwolfapi/models/message.py
xwolfapi/models/subscriber.py
xwolfapi-1.0.0.dist-info/METADATA
xwolfapi-1.0.0.dist-info/WHEEL
xwolfapi-1.0.0.dist-info/top_level.txt
xwolfapi-1.0.0.dist-info/RECORD
